kinesyslog/__init__.py
kinesyslog/commands.py
kinesyslog/constant.py
kinesyslog/gelf.py
kinesyslog/init.py
kinesyslog/message.py
kinesyslog/prometheus.py
kinesyslog/protocol.py
kinesyslog/proxy.py
kinesyslog/ringbuffer.py
kinesyslog/server.py
kinesyslog/sink.py
kinesyslog/spool.py
kinesyslog/stats.py
kinesyslog/util.py
kinesyslog-2.0.1.dist-info/LICENSE
kinesyslog-2.0.1.dist-info/METADATA
kinesyslog-2.0.1.dist-info/WHEEL
kinesyslog-2.0.1.dist-info/entry_points.txt
kinesyslog-2.0.1.dist-info/top_level.txt
kinesyslog-2.0.1.dist-info/version.txt
kinesyslog-2.0.1.dist-info/version_full.txt
kinesyslog-2.0.1.dist-info/RECORD
