Metadata-Version: 2.1
Name: kinesyslog
Version: 2.0.1
Summary: Syslog and GELF relay to AWS Kinesis Firehose. Supports UDP, TCP, and TLS; RFC3164, RFC5424, RFC5425, RFC6587, GELF v1.1.
Home-page: https://github.com/brandond/kinesyslog
Author: Brandon Davidson
Author-email: brad@oatmail.org
License: UNKNOWN
Platform: UNKNOWN
Classifier: Development Status :: 5 - Production/Stable
Classifier: Environment :: No Input/Output (Daemon)
Classifier: Framework :: AsyncIO
Classifier: License :: OSI Approved :: Apache Software License
Classifier: Operating System :: POSIX :: Linux
Classifier: Programming Language :: Python :: 3.5
Classifier: Programming Language :: Python :: 3.6
Classifier: Topic :: Internet :: Log Analysis
Classifier: Topic :: System :: Logging
Requires-Python: >=3.5
Requires-Dist: boto3 (>=1.9.86)
Requires-Dist: botocore (>=1.12.86)
Requires-Dist: click
Requires-Dist: ujson (<2.0.0)
Requires-Dist: msgpack
Provides-Extra: all
Requires-Dist: setproctitle (>=1.1.10); extra == 'all'
Requires-Dist: aiohttp (>=3.5.4); extra == 'all'
Requires-Dist: aioprometheus (>=18.7.1); extra == 'all'
Provides-Extra: dev
Requires-Dist: setuptools-version-command; extra == 'dev'
Provides-Extra: prometheus
Requires-Dist: aiohttp (>=3.5.4); extra == 'prometheus'
Requires-Dist: aioprometheus (>=18.7.1); extra == 'prometheus'
